yaag.py
yaag-0.0.1.dist-info/LICENSE
yaag-0.0.1.dist-info/WHEEL
yaag-0.0.1.dist-info/METADATA
yaag-0.0.1.dist-info/RECORD
